moviesViewEstimator/__init__.py
moviesViewEstimator/linear_regression_model.pickle
moviesViewEstimator/model.py
tests/__init__.py
tests/conftest.py
tests/test_model.py
moviesViewEstimator-0.0.8.dist-info/LICENSE
moviesViewEstimator-0.0.8.dist-info/METADATA
moviesViewEstimator-0.0.8.dist-info/WHEEL
moviesViewEstimator-0.0.8.dist-info/top_level.txt
moviesViewEstimator-0.0.8.dist-info/RECORD
