Metadata-Version: 2.1
Name: moviesViewEstimator
Version: 0.0.8
Summary: UNKNOWN
Home-page: https://github.com/Joaopeuko/moviesViewEstimator
Author: Joao Paulo Euko
License: MIT
Platform: UNKNOWN
License-File: LICENSE
Requires-Dist: pandas
Requires-Dist: pytest
Requires-Dist: sklearn
Requires-Dist: coverage
Requires-Dist: setuptools
Requires-Dist: pytest-cov
